autonova/__init__.py
autonova/auto.py
autonova/main.py
autonova/autonova/__init__.py
autonova/autonova/data_balancing.py
autonova/autonova/data_featureEngineering.py
autonova/autonova/data_featureselection.py
autonova/autonova/data_preprocessing.py
autonova/autonova/data_spliting.py
autonova/autonova/data_transformation.py
autonova/meta_learning/__init__.py
autonova/meta_learning/meta.py
autonova/pipeline/__init__.py
autonova/pipeline/preprocessing.py
autonova/test/__init__.py
autonova/test/test_model_pipeline.py
autonova/utils/__init__.py
autonova/utils/utils.py
autonova-1.0.2.dist-info/licenses/LICENSE
autonova-1.0.2.dist-info/METADATA
autonova-1.0.2.dist-info/WHEEL
autonova-1.0.2.dist-info/top_level.txt
autonova-1.0.2.dist-info/RECORD
