Metadata-Version: 2.4
Name: autonova
Version: 1.0.2
Summary: An automated machine learning pipeline with all-at-one-click feature.
Home-page: https://github.com/Sanjaypal1916/ProjectX
Author: Sanjay Pal
Author-email: sanjaypal606060@gmail.com
License: MIT
Classifier: License :: OSI Approved :: MIT License
Classifier: Programming Language :: Python :: 3
Classifier: Operating System :: OS Independent
Requires-Python: >=3.7
License-File: LICENSE
Requires-Dist: catboost
Requires-Dist: imbalanced-learn
Requires-Dist: joblib
Requires-Dist: lightgbm
Requires-Dist: numpy
Requires-Dist: optuna
Requires-Dist: optuna-integration
Requires-Dist: pandas
Requires-Dist: pytest
Requires-Dist: scikit-learn
Requires-Dist: xgboost
Dynamic: author
Dynamic: author-email
Dynamic: classifier
Dynamic: description
Dynamic: description-content-type
Dynamic: home-page
Dynamic: license
Dynamic: license-file
Dynamic: requires-dist
Dynamic: requires-python
Dynamic: summary
